{
  "pools": [
      {
          "rolls": 1,
          "entries": [
              {
                  "type": "minecraft:item",
                  "weight": 9,
                  "name": "minecraft:prismarine_shard",
                  "functions": [
                      {
                          "function": "minecraft:set_count",
                          "count": {
                              "min": 0,
                              "max": 2
                          }
                      }
                  ]
              },
              {
                  "type": "minecraft:item",
                  "weight": 1,
                  "name": "minecraft:prismarine_crystals",
                  "functions": [
                      {
                          "function": "minecraft:set_count",
                          "count": {
                              "min": 0,
                              "max": 1
                          }
                      }
                  ]
              }
          ]
      }
  ]
}